MANIFEST.in
README.md
requirements-dev.txt
requirements.txt
setup.py
coords_transformer/__init__.py
coords_transformer/constants.py
coords_transformer/coords_calculation.py
coords_transformer/version.py
coords_transformer.egg-info/PKG-INFO
coords_transformer.egg-info/SOURCES.txt
coords_transformer.egg-info/dependency_links.txt
coords_transformer.egg-info/requires.txt
coords_transformer.egg-info/top_level.txt
coords_transformer/filename/__init__.py
coords_transformer/filename/factory.py
coords_transformer/filename/filename.py
coords_transformer/point/__init__.py
coords_transformer/point/factory.py
coords_transformer/point/point.py
coords_transformer/point/service.py