Metadata-Version: 2.1
Name: coords-transformer
Version: 0.0.5
Summary: Transform pixel coordinates to latitude and longitude, and vise versa.
Home-page: https://github.com/sagri-tokyo/coordinates-transformer
Author: tsurutan
Author-email: tsurutan.android@gmail.com
License: MIT
Keywords: coordinates transformer
Platform: UNKNOWN
Classifier: License :: OSI Approved :: MIT License
Classifier: Programming Language :: Python :: 3.6
Classifier: Programming Language :: Python :: 3.7
Classifier: Programming Language :: Python :: 3.8
